youtube_watcher
