Metadata-Version: 1.0
Name: youtube-watcher
Version: 0.10.5
Summary: A simple program to list new YouTube videos and download them
Home-page: https://github.com/Sjc1000/youtube_watcher
Author: Steven J. Core
Author-email: 42Echo6Alpha@gmail.com
License: GPL3.0
Platform: UNKNOWN
